Topsis_Kushagar/102003002.py
Topsis_Kushagar/__init__.py
Topsis_Kushagar_102003002-0.0.2.dist-info/LICENSE
Topsis_Kushagar_102003002-0.0.2.dist-info/METADATA
Topsis_Kushagar_102003002-0.0.2.dist-info/WHEEL
Topsis_Kushagar_102003002-0.0.2.dist-info/entry_points.txt
Topsis_Kushagar_102003002-0.0.2.dist-info/top_level.txt
Topsis_Kushagar_102003002-0.0.2.dist-info/RECORD
