Metadata-Version: 2.1
Name: Topsis-Kushagar-102003002
Version: 0.0.2
Summary: It is a package for performing TOPSIS analysis
Author: Kushagar Bansal
License: MIT
License-File: LICENSE
Requires-Dist: pandas
